pyhmmer/__init__.py
pyhmmer/daemon.cpython-39-darwin.so
pyhmmer/daemon.pxd
pyhmmer/daemon.pyi
pyhmmer/daemon.pyx
pyhmmer/easel.cpython-39-darwin.so
pyhmmer/easel.pxd
pyhmmer/easel.pyi
pyhmmer/easel.pyx
pyhmmer/errors.cpython-39-darwin.so
pyhmmer/errors.pyi
pyhmmer/errors.pyx
pyhmmer/exceptions.pxi
pyhmmer/hmmer.py
pyhmmer/plan7.cpython-39-darwin.so
pyhmmer/plan7.pxd
pyhmmer/plan7.pyi
pyhmmer/plan7.pyx
pyhmmer/py.typed
pyhmmer/utils.py
pyhmmer/fileobj/bsd.pxi
pyhmmer/fileobj/linux.pxi
pyhmmer/reexports/__init__.pxd
pyhmmer/reexports/esl_sqio_ascii.h
pyhmmer/reexports/esl_sqio_ascii.pxd
pyhmmer/reexports/p7_hmmfile.h
pyhmmer/reexports/p7_hmmfile.pxd
pyhmmer/reexports/p7_tophits.h
pyhmmer/reexports/p7_tophits.pxd
pyhmmer/tests/__init__.py
pyhmmer/tests/requirements.txt
pyhmmer/tests/test_doctest.py
pyhmmer/tests/test_errors.py
pyhmmer/tests/test_hmmer.py
pyhmmer/tests/utils.py
pyhmmer/tests/data/README.md
pyhmmer/tests/data/hmms/make.sh
pyhmmer/tests/data/hmms/bin/PF02826.h3m
pyhmmer/tests/data/hmms/bin/PKSI-AT.h3m
pyhmmer/tests/data/hmms/bin/Thioesterase.h3m
pyhmmer/tests/data/hmms/bin/t2pks.h3m
pyhmmer/tests/data/hmms/db/PF02826.hmm
pyhmmer/tests/data/hmms/db/PF02826.hmm.h3f
pyhmmer/tests/data/hmms/db/PF02826.hmm.h3i
pyhmmer/tests/data/hmms/db/PF02826.hmm.h3m
pyhmmer/tests/data/hmms/db/PF02826.hmm.h3p
pyhmmer/tests/data/hmms/db/PKSI-AT.hmm
pyhmmer/tests/data/hmms/db/PKSI-AT.hmm.h3f
pyhmmer/tests/data/hmms/db/PKSI-AT.hmm.h3i
pyhmmer/tests/data/hmms/db/PKSI-AT.hmm.h3m
pyhmmer/tests/data/hmms/db/PKSI-AT.hmm.h3p
pyhmmer/tests/data/hmms/db/Thioesterase.hmm
pyhmmer/tests/data/hmms/db/Thioesterase.hmm.h3f
pyhmmer/tests/data/hmms/db/Thioesterase.hmm.h3i
pyhmmer/tests/data/hmms/db/Thioesterase.hmm.h3m
pyhmmer/tests/data/hmms/db/Thioesterase.hmm.h3p
pyhmmer/tests/data/hmms/db/t2pks.hmm
pyhmmer/tests/data/hmms/db/t2pks.hmm.h3f
pyhmmer/tests/data/hmms/db/t2pks.hmm.h3i
pyhmmer/tests/data/hmms/db/t2pks.hmm.h3m
pyhmmer/tests/data/hmms/db/t2pks.hmm.h3p
pyhmmer_arm-0.7.5.dist-info/COPYING
pyhmmer_arm-0.7.5.dist-info/METADATA
pyhmmer_arm-0.7.5.dist-info/WHEEL
pyhmmer_arm-0.7.5.dist-info/top_level.txt
pyhmmer_arm-0.7.5.dist-info/RECORD
