Metadata-Version: 2.1
Name: pyhmmer-arm
Version: 0.7.5
Summary: Cython bindings and Python interface to HMMER3.
Home-page: https://github.com/althonos/pyhmmer
Author: Martin Larralde
Author-email: martin.larralde@embl.de
License: MIT
Project-URL: Documentation, https://pyhmmer.readthedocs.io/en/stable/
Project-URL: Bug Tracker, https://github.com/althonos/pyhmmer/issues
Project-URL: Changelog, https://github.com/althonos/pyhmmer/blob/master/CHANGELOG.md
Project-URL: Coverage, https://codecov.io/gh/althonos/pyhmmer/
Project-URL: Builds, https://git.embl.de/larralde/pyhmmer/-/pipelines
Project-URL: Zenodo, https://doi.org/10.5281/zenodo.4270012
Project-URL: PyPI, https://pypi.org/project/pyhmmer
Keywords: bioinformatics,profile,HMM,sequence,pfam
Platform: posix
Classifier: Development Status :: 4 - Beta
Classifier: Intended Audience :: Developers
Classifier: Intended Audience :: Science/Research
Classifier: License :: OSI Approved :: MIT License
Classifier: Operating System :: POSIX
Classifier: Programming Language :: C
Classifier: Programming Language :: Cython
Classifier: Programming Language :: Python :: 3.6
Classifier: Programming Language :: Python :: 3.7
Classifier: Programming Language :: Python :: 3.8
Classifier: Programming Language :: Python :: 3.9
Classifier: Programming Language :: Python :: 3.10
Classifier: Programming Language :: Python :: 3.11
Classifier: Programming Language :: Python :: Implementation :: CPython
Classifier: Programming Language :: Python :: Implementation :: PyPy
Classifier: Topic :: Scientific/Engineering :: Bio-Informatics
Classifier: Topic :: Scientific/Engineering :: Medical Science Apps.
Classifier: Typing :: Typed
Requires-Python: >=3.6
License-File: COPYING
Requires-Dist: psutil (~=5.8)
